gpgedit.py
gpgedit-0.0.8.dist-info/METADATA
gpgedit-0.0.8.dist-info/RECORD
gpgedit-0.0.8.dist-info/WHEEL
gpgedit-0.0.8.dist-info/entry_points.txt
gpgedit-0.0.8.dist-info/top_level.txt
