Metadata-Version: 2.1
Name: gpgedit
Version: 0.0.8
Summary: GpgEdit lets you edit a gpg-encrypted file
Home-page: https://github.com/bachew/gpgedit
Author: Chew Boon Aik
Author-email: bachew@gmail.com
License: MIT
Download-URL: https://github.com/bachew/gpgedit/archive/master.zip
Platform: UNKNOWN
Classifier: Development Status :: 4 - Beta
Classifier: Environment :: Console
Classifier: License :: OSI Approved :: MIT License
Classifier: Operating System :: Unix
Classifier: Programming Language :: Python :: 2.7
Classifier: Programming Language :: Python :: 3
Classifier: Topic :: Software Development :: Build Tools
Classifier: Topic :: Utilities
Requires-Dist: click (>=6.7)
Requires-Dist: gevent (>=1.2.2)
